{
  "results": [
    {
      "hits": [
        {
          "productBuyable": true,
          "_tags": [
            "product",
            "mkp",
            "dcom",
            "inno",
            "pub"
          ],
          "pubSearchText": "Sacoche pour ordinateur portable Doro dorocase8080tr - case doro 8062/8080 transp dorocase 8080 tr - case doro 8062 / 8080 transp MC348242466",
          "priceSort": 2499,
          "filters": [
            "product",
            "mkp",
            "dcom",
            "inno",
            "pub"
          ],
          "dataSrc": "DCOM",
          "searchTextWithPointsForts": "Sacoche pour ordinateur portable Doro dorocase8080tr - case doro 8062/8080 transp dorocase 8080 tr - case doro 8062 / 8080 transp ",
          "codic": "MC348242466",
          "productMarketplace": true,
          "sort": {
            "offreActive": false,
            "dartyComSort": 0,
            "storeCount": 0,
            "statusSort": 3000,
            "crossSellSort": 0,
            "innoAvailSort": {},
            "stripedPriceSort": 0,
            "accessory": false,
            "saleLevelsByPeriods": {
              "1": 0,
              "2": 0,
              "3": 0,
              "4": 0,
              "5": 0,
              "6": 0,
              "7": 0,
              "14": 0,
              "21": 0,
              "30": 0
            },
            "stockQuantity": 0,
            "revenuesByPeriods": {
              "1": 0,
              "2": 0,
              "3": 0,
              "4": 0,
              "5": 0,
              "6": 0,
              "7": 0,
              "14": 0,
              "21": 0,
              "30": 0
            },
            "salesLevel": 0,
            "publishedDate": 0,
            "packEcoMember": false,
            "prices": {
              "907040": 2499
            },
            "refDcom": 2499,
            "px12": 0,
            "px24": 0,
            "contextualizedPrices": null,
            "pxSe": 0
          },
          "category": 1136,
          "prices": {
            "stores": {
              "907040": 2499,
              "000000": 0
            },
            "refDcom": 2499,
            "vat": 20
          },
          "revenuesByPeriods": {
            "1": 0,
            "2": 0,
            "3": 0,
            "4": 0,
            "5": 0,
            "6": 0,
            "7": 0,
            "14": 0,
            "21": 0,
            "30": 0
          },
          "saleLevelsByPeriods": {
            "1": 0,
            "2": 0,
            "3": 0,
            "4": 0,
            "5": 0,
            "6": 0,
            "7": 0,
            "14": 0,
            "21": 0,
            "30": 0
          },
          "categoryFrontInno": 0,
          "lowPrice": false,
          "publishedDateSort": 0,
          "brand": "DORO",
          "searchText": "Sacoche pour ordinateur portable Doro dorocase8080tr - case doro 8062/8080 transp dorocase 8080 tr - case doro 8062 / 8080 transp",
          "ean": [
            "7322460076689"
          ],
          "characs": [
            {
              "name": "Caractéristiques complémentaires",
              "id": "368237",
              "value": "Type de sacoche : Housse",
              "unit": ""
            }
          ],
          "pictures": [
            {
              "date": "2023/01/27",
              "name": "21355518_3723_1.jpg",
              "algoliaPict": "market/2023/01/27/21355518_3723_1.jpg",
              "zoom": true
            }
          ],
          "reviewsAvgRatingSort": 0,
          "usedOfferDarty": false,
          "oldCodics": [
            "MK1109981646",
            "MK931191771"
          ],
          "brandsByCategories": [
            "12439:DORO",
            "search:DORO",
            "1136:DORO",
            "26055:DORO",
            "6:DORO",
            "30072:DORO",
            "1:DORO"
          ],
          "usedOffer": false,
          "_highlightResult": {
            "brandName": {
              "value": "<em>Doro</em>",
              "matchLevel": "partial",
              "fullyHighlighted": true,
              "matchedWords": [
                "doro"
              ]
            },
            "categoryName": {
              "value": "Sacoche pour ordinateur portable",
              "matchLevel": "none",
              "matchedWords": []
            },
            "searchText": {
              "value": "Sacoche pour ordinateur portable <em>Doro</em> dorocase8080tr - case <em>doro</em> 8062/<em>8080</em> transp dorocase <em>8080</em> tr - case <em>doro</em> 8062 / <em>8080</em> transp",
              "matchLevel": "full",
              "fullyHighlighted": false,
              "matchedWords": [
                "doro",
                "8080"
              ]
            }
          },
          "categoryName": "Sacoche pour ordinateur portable",
          "salesLevelSort": 0,
          "newOfferDarty": false,
          "objectID": "MC348242466",
          "visibility": [
            "DCOM",
            "INNO"
          ],
          "reference": "dorocase8080tr - case doro 8062/8080 transp",
          "preOrderable": false,
          "source": "BOMP",
          "facets": [
            "brand_DORO",
            "seller_311050",
            "category_1136",
            "vendumkp_1",
            "new_offer",
            "webonly_1"
          ],
          "pourAdulte": false,
          "newOffer": true,
          "status": {
            "filiales": [
              {
                "compact": "GPART"
              }
            ],
            "defaultCompact": "GPART"
          },
          "brandName": "Doro",
          "nature": "PRODUCT",
          "publication": [
            "DCOM",
            "INNO"
          ],
          "salesLevel": 0,
          "inventory": {
            "sellers": [
              311050
            ]
          },
          "productAccessory": false,
          "data": {},
          "inStock": true
        },
        {
          "productBuyable": true,
          "inventory": {
            "sellers": [
              311091
            ]
          },
          "status": {
            "filiales": [
              {
                "compact": "GPART"
              }
            ],
            "defaultCompact": "GPART"
          },
          "searchText": "Coque et étui téléphone mobile Doro Coque 8080 - elégante Coque 8080 - elégante",
          "pourAdulte": false,
          "categoryFrontInno": 0,
          "saleLevelsByPeriods": {
            "1": 0,
            "2": 0,
            "3": 0,
            "4": 0,
            "5": 0,
            "6": 0,
            "7": 0,
            "14": 0,
            "21": 0,
            "30": 0
          },
          "categoryName": "Coque et étui téléphone mobile",
          "newOffer": true,
          "_tags": [
            "product",
            "dcom",
            "mkp",
            "dpro",
            "inno",
            "pub"
          ],
          "category": 708,
          "facets": [
            "category_708",
            "brand_DORO",
            "seller_311091",
            "vendumkp_1",
            "new_offer",
            "webonly_1"
          ],
          "inStock": true,
          "newOfferDarty": false,
          "usedOfferDarty": false,
          "_highlightResult": {
            "brandName": {
              "value": "<em>Doro</em>",
              "matchLevel": "partial",
              "fullyHighlighted": true,
              "matchedWords": [
                "doro"
              ]
            },
            "categoryName": {
              "value": "Coque et étui téléphone mobile",
              "matchLevel": "none",
              "matchedWords": []
            },
            "searchText": {
              "value": "Coque et étui téléphone mobile <em>Doro</em> Coque <em>8080</em> - elégante Coque <em>8080</em> - elégante",
              "matchLevel": "full",
              "fullyHighlighted": false,
              "matchedWords": [
                "doro",
                "8080"
              ]
            }
          },
          "productAccessory": false,
          "objectID": "MC348171726",
          "revenuesByPeriods": {
            "1": 0,
            "2": 0,
            "3": 0,
            "4": 0,
            "5": 0,
            "6": 0,
            "7": 0,
            "14": 0,
            "21": 0,
            "30": 0
          },
          "oldCodics": [
            "MK573862008"
          ],
          "priceSort": 4534,
          "publishedDateSort": 0,
          "prices": {
            "stores": {
              "907040": 4534,
              "000000": 0
            },
            "refDcom": 4534,
            "vat": 20
          },
          "source": "BOMP",
          "salesLevelSort": 0,
          "codic": "MC348171726",
          "publication": [
            "DPRO",
            "DCOM",
            "INNO"
          ],
          "filters": [
            "product",
            "dcom",
            "mkp",
            "dpro",
            "inno",
            "pub"
          ],
          "brandName": "Doro",
          "brandsByCategories": [
            "search:DORO",
            "29052:DORO",
            "26058:DORO",
            "89054:DORO",
            "6:DORO",
            "708:DORO"
          ],
          "searchTextWithPointsForts": "Coque et étui téléphone mobile Doro Coque 8080 - elégante Coque 8080 - elégante ",
          "brand": "DORO",
          "sort": {
            "offreActive": false,
            "dartyComSort": 0,
            "storeCount": 0,
            "statusSort": 3000,
            "crossSellSort": 0,
            "innoAvailSort": {},
            "stripedPriceSort": 0,
            "accessory": false,
            "saleLevelsByPeriods": {
              "1": 0,
              "2": 0,
              "3": 0,
              "4": 0,
              "5": 0,
              "6": 0,
              "7": 0,
              "14": 0,
              "21": 0,
              "30": 0
            },
            "stockQuantity": 0,
            "revenuesByPeriods": {
              "1": 0,
              "2": 0,
              "3": 0,
              "4": 0,
              "5": 0,
              "6": 0,
              "7": 0,
              "14": 0,
              "21": 0,
              "30": 0
            },
            "salesLevel": 0,
            "publishedDate": 0,
            "packEcoMember": false,
            "prices": {
              "907040": 4534
            },
            "refDcom": 4534,
            "px12": 0,
            "px24": 0,
            "contextualizedPrices": null,
            "pxSe": 0
          },
          "usedOffer": false,
          "nature": "PRODUCT",
          "data": {},
          "visibility": [
            "DCOM",
            "DPRO",
            "INNO"
          ],
          "productMarketplace": true,
          "reference": "Coque 8080 - elégante",
          "dataSrc": "DCOM",
          "preOrderable": false,
          "pictures": [
            {
              "date": "2023/01/30",
              "name": "21345299_3723_1.jpg",
              "algoliaPict": "market/2023/01/30/21345299_3723_1.jpg",
              "zoom": true
            }
          ],
          "ean": [
            "7322460076535"
          ],
          "salesLevel": 0,
          "reviewsAvgRatingSort": 0,
          "lowPrice": false,
          "pubSearchText": "Coque et étui téléphone mobile Doro Coque 8080 - elégante Coque 8080 - elégante MC348171726"
        },
        {
          "category": 715,
          "pictures": [
            {
              "date": "2023/01/30",
              "name": "21345300_3723_1.jpg",
              "algoliaPict": "market/2023/01/30/21345300_3723_1.jpg",
              "zoom": true
            }
          ],
          "ean": [
            "7322460076764"
          ],
          "codic": "MC348171714",
          "oldCodics": [
            "MK573862006"
          ],
          "sort": {
            "offreActive": false,
            "dartyComSort": 0,
            "storeCount": 0,
            "statusSort": 3000,
            "crossSellSort": 0,
            "innoAvailSort": {},
            "stripedPriceSort": 0,
            "accessory": false,
            "saleLevelsByPeriods": {
              "1": 0,
              "2": 0,
              "3": 0,
              "4": 0,
              "5": 0,
              "6": 0,
              "7": 0,
              "14": 0,
              "21": 0,
              "30": 0
            },
            "stockQuantity": 0,
            "revenuesByPeriods": {
              "1": 0,
              "2": 0,
              "3": 0,
              "4": 0,
              "5": 0,
              "6": 0,
              "7": 0,
              "14": 0,
              "21": 0,
              "30": 0
            },
            "salesLevel": 0,
            "publishedDate": 0,
            "packEcoMember": false,
            "prices": {
              "907040": 3560
            },
            "refDcom": 3560,
            "px12": 0,
            "px24": 0,
            "contextualizedPrices": null,
            "pxSe": 0
          },
          "productBuyable": true,
          "_tags": [
            "product",
            "dcom",
            "mkp",
            "dpro",
            "inno",
            "pub"
          ],
          "newOffer": true,
          "lowPrice": false,
          "reviewsAvgRatingSort": 0,
          "preOrderable": false,
          "brand": "DORO",
          "productAccessory": false,
          "searchTextWithPointsForts": "Protection d'écran pour smartphone Doro Film de protection 8080 noir Film de protection 8080 noir ",
          "status": {
            "filiales": [
              {
                "compact": "GPART"
              }
            ],
            "defaultCompact": "GPART"
          },
          "_highlightResult": {
            "brandName": {
              "value": "<em>Doro</em>",
              "matchLevel": "partial",
              "fullyHighlighted": true,
              "matchedWords": [
                "doro"
              ]
            },
            "categoryName": {
              "value": "Protection d'écran pour smartphone",
              "matchLevel": "none",
              "matchedWords": []
            },
            "searchText": {
              "value": "Protection d'écran pour smartphone <em>Doro</em> Film de protection <em>8080</em> noir Film de protection <em>8080</em> noir",
              "matchLevel": "full",
              "fullyHighlighted": false,
              "matchedWords": [
                "doro",
                "8080"
              ]
            }
          },
          "facets": [
            "brand_DORO",
            "category_715",
            "seller_312126",
            "vendumkp_1",
            "new_offer",
            "webonly_1"
          ],
          "categoryFrontInno": 0,
          "visibility": [
            "DCOM",
            "DPRO",
            "INNO"
          ],
          "inventory": {
            "sellers": [
              312126
            ]
          },
          "usedOfferDarty": false,
          "newOfferDarty": false,
          "categoryName": "Protection d'écran pour smartphone",
          "source": "BOMP",
          "saleLevelsByPeriods": {
            "1": 0,
            "2": 0,
            "3": 0,
            "4": 0,
            "5": 0,
            "6": 0,
            "7": 0,
            "14": 0,
            "21": 0,
            "30": 0
          },
          "salesLevel": 0,
          "publishedDateSort": 0,
          "pubSearchText": "Protection d'écran pour smartphone Doro Film de protection 8080 noir Film de protection 8080 noir MC348171714",
          "pourAdulte": false,
          "reference": "Film de protection 8080 noir",
          "nature": "PRODUCT",
          "dataSrc": "DCOM",
          "revenuesByPeriods": {
            "1": 0,
            "2": 0,
            "3": 0,
            "4": 0,
            "5": 0,
            "6": 0,
            "7": 0,
            "14": 0,
            "21": 0,
            "30": 0
          },
          "inStock": true,
          "brandName": "Doro",
          "filters": [
            "product",
            "dcom",
            "mkp",
            "dpro",
            "inno",
            "pub"
          ],
          "salesLevelSort": 0,
          "usedOffer": false,
          "productMarketplace": true,
          "publication": [
            "DPRO",
            "DCOM",
            "INNO"
          ],
          "searchText": "Protection d'écran pour smartphone Doro Film de protection 8080 noir Film de protection 8080 noir",
          "brandsByCategories": [
            "715:DORO",
            "search:DORO",
            "29052:DORO",
            "26058:DORO",
            "89054:DORO",
            "6:DORO"
          ],
          "priceSort": 3560,
          "prices": {
            "stores": {
              "907040": 3560,
              "000000": 0
            },
            "refDcom": 3560,
            "vat": 20
          },
          "data": {},
          "objectID": "MC348171714"
        },
        {
          "productBuyable": true,
          "status": {
            "filiales": [
              {
                "compact": "GPART"
              }
            ],
            "defaultCompact": "GPART"
          },
          "reference": "Film de protection 8080 blanc",
          "dataSrc": "DCOM",
          "usedOffer": false,
          "filters": [
            "product",
            "dcom",
            "mkp",
            "dpro",
            "inno",
            "pub"
          ],
          "categoryName": "Protection d'écran pour smartphone",
          "source": "BOMP",
          "newOfferDarty": false,
          "data": {},
          "publication": [
            "DPRO",
            "DCOM",
            "INNO"
          ],
          "inStock": true,
          "searchText": "Protection d'écran pour smartphone Doro Film de protection 8080 blanc Film de protection 8080 blanc",
          "preOrderable": false,
          "brand": "DORO",
          "publishedDateSort": 0,
          "codic": "MC348171307",
          "brandName": "Doro",
          "brandsByCategories": [
            "715:DORO",
            "search:DORO",
            "29052:DORO",
            "26058:DORO",
            "89054:DORO",
            "6:DORO"
          ],
          "visibility": [
            "DCOM",
            "DPRO",
            "INNO"
          ],
          "inventory": {
            "sellers": [
              311091,
              312306
            ]
          },
          "oldCodics": [
            "MK573862007",
            "MK1109954744"
          ],
          "pubSearchText": "Protection d'écran pour smartphone Doro Film de protection 8080 blanc Film de protection 8080 blanc MC348171307",
          "salesLevel": 0,
          "revenuesByPeriods": {
            "1": 0,
            "2": 0,
            "3": 0,
            "4": 0,
            "5": 0,
            "6": 0,
            "7": 0,
            "14": 0,
            "21": 0,
            "30": 0
          },
          "reviewsAvgRatingSort": 0,
          "_tags": [
            "product",
            "dcom",
            "mkp",
            "dpro",
            "inno",
            "pub"
          ],
          "newOffer": true,
          "ean": [
            "7322460076603"
          ],
          "saleLevelsByPeriods": {
            "1": 0,
            "2": 0,
            "3": 0,
            "4": 0,
            "5": 0,
            "6": 0,
            "7": 0,
            "14": 0,
            "21": 0,
            "30": 0
          },
          "nature": "PRODUCT",
          "salesLevelSort": 0,
          "facets": [
            "seller_311091",
            "vendumkp_1",
            "seller_312306",
            "webonly_1",
            "brand_DORO",
            "new_offer",
            "category_715"
          ],
          "categoryFrontInno": 0,
          "productAccessory": false,
          "_highlightResult": {
            "brandName": {
              "value": "<em>Doro</em>",
              "matchLevel": "partial",
              "fullyHighlighted": true,
              "matchedWords": [
                "doro"
              ]
            },
            "categoryName": {
              "value": "Protection d'écran pour smartphone",
              "matchLevel": "none",
              "matchedWords": []
            },
            "searchText": {
              "value": "Protection d'écran pour smartphone <em>Doro</em> Film de protection <em>8080</em> blanc Film de protection <em>8080</em> blanc",
              "matchLevel": "full",
              "fullyHighlighted": false,
              "matchedWords": [
                "doro",
                "8080"
              ]
            }
          },
          "usedOfferDarty": false,
          "priceSort": 2706,
          "searchTextWithPointsForts": "Protection d'écran pour smartphone Doro Film de protection 8080 blanc Film de protection 8080 blanc ",
          "objectID": "MC348171307",
          "category": 715,
          "pictures": [
            {
              "date": "2023/01/30",
              "name": "21343435_3723_1.jpg",
              "algoliaPict": "market/2023/01/30/21343435_3723_1.jpg",
              "zoom": true
            }
          ],
          "prices": {
            "stores": {
              "907040": 2706,
              "000000": 0
            },
            "refDcom": 2706,
            "vat": 20
          },
          "pourAdulte": false,
          "productMarketplace": true,
          "sort": {
            "offreActive": false,
            "dartyComSort": 0,
            "storeCount": 0,
            "statusSort": 3000,
            "crossSellSort": 0,
            "innoAvailSort": {},
            "stripedPriceSort": 0,
            "accessory": false,
            "saleLevelsByPeriods": {
              "1": 0,
              "2": 0,
              "3": 0,
              "4": 0,
              "5": 0,
              "6": 0,
              "7": 0,
              "14": 0,
              "21": 0,
              "30": 0
            },
            "stockQuantity": 0,
            "revenuesByPeriods": {
              "1": 0,
              "2": 0,
              "3": 0,
              "4": 0,
              "5": 0,
              "6": 0,
              "7": 0,
              "14": 0,
              "21": 0,
              "30": 0
            },
            "salesLevel": 0,
            "publishedDate": 0,
            "packEcoMember": false,
            "prices": {
              "907040": 2706
            },
            "refDcom": 2706,
            "px12": 0,
            "px24": 0,
            "contextualizedPrices": null,
            "pxSe": 0
          },
          "lowPrice": false
        }
      ],
      "nbHits": 72,
      "hitsPerPage": 4,
      "index": "darty_prod_es6",
      "page": 0,
      "nbPages": 18,
      "processingTimeMS": 6,
      "processingTimingsMS": {
        "afterFetch": {
          "total": 1
        },
        "fetch": {
          "total": 5,
          "query": 1,
          "scanning": 3
        },
        "total": 6
      },
      "exhaustiveNbHits": true,
      "exhaustiveTypo": true,
      "query": "doro 8080",
      "queryAfterRemoval": "doro 8080",
      "params": "query=doro+8080&hitsPerPage=4&tagFilters=%5B%22dcom%22%5D",
      "exhaustive": {
        "nbHits": true,
        "typo": true
      }
    },
    {
      "hits": [
        {
          "objectID": "doro 8080",
          "_highlightResult": {
            "query": {
              "value": "<em>doro</em> <em>8080</em>",
              "matchLevel": "full",
              "fullyHighlighted": true,
              "matchedWords": [
                "doro",
                "8080"
              ]
            }
          },
          "darty_prod_es6": {
            "exact_nb_hits": 8,
            "facets": {
              "exact_matches": {},
              "analytics": {}
            }
          },
          "nb_words": 2,
          "popularity": 55,
          "query": "doro 8080"
        },
        {
          "popularity": 60,
          "query": "doro 8050",
          "objectID": "doro 8050",
          "_highlightResult": {
            "query": {
              "value": "<em>doro</em> <em>8050</em>",
              "matchLevel": "full",
              "fullyHighlighted": true,
              "matchedWords": [
                "doro",
                "8080"
              ]
            }
          },
          "darty_prod_es6": {
            "exact_nb_hits": 9,
            "facets": {
              "exact_matches": {},
              "analytics": {}
            }
          },
          "nb_words": 2
        }
      ],
      "nbHits": 2,
      "hitsPerPage": 5,
      "index": "darty_prod_es6_query_suggestions",
      "page": 0,
      "nbPages": 1,
      "processingTimeMS": 1,
      "exhaustiveNbHits": true,
      "exhaustiveTypo": true,
      "query": "doro 8080",
      "params": "query=doro+8080&hitsPerPage=5",
      "exhaustive": {
        "nbHits": true,
        "typo": true
      }
    }
  ]
}
